znframe/__init__.py
znframe/bonds/__init__.py
znframe/frame.py
znframe-0.1.5.dist-info/METADATA
znframe-0.1.5.dist-info/WHEEL
znframe-0.1.5.dist-info/RECORD
